{"trial_id": "075", "hyperparameters": {"space": [{"class_name": "Int", "config": {"name": "num_layers", "default": null, "conditions": [], "min_value": 2, "max_value": 20, "step": 1, "sampling": "linear"}}, {"class_name": "Int", "config": {"name": "units_0", "default": null, "conditions": [], "min_value": 16, "max_value": 512, "step": 32, "sampling": "linear"}}, {"class_name": "Choice", "config": {"name": "activation_0", "default": "relu", "conditions": [], "values": ["relu", "leaky_relu", "swish", "gelu", "mish"], "ordered": false}}, {"class_name": "Float", "config": {"name": "dropout_0", "default": 0.1, "conditions": [], "min_value": 0.1, "max_value": 0.7, "step": 0.1, "sampling": "linear"}}, {"class_name": "Int", "config": {"name": "units_1", "default": null, "conditions": [], "min_value": 16, "max_value": 512, "step": 32, "sampling": "linear"}}, {"class_name": "Choice", "config": {"name": "activation_1", "default": "relu", "conditions": [], "values": ["relu", "leaky_relu", "swish", "gelu", "mish"], "ordered": false}}, {"class_name": "Float", "config": {"name": "dropout_1", "default": 0.1, "conditions": [], "min_value": 0.1, "max_value": 0.7, "step": 0.1, "sampling": "linear"}}, {"class_name": "Choice", "config": {"name": "learning_rate", "default": 0.005, "conditions": [], "values": [0.005, 0.001, 0.0005], "ordered": true}}, {"class_name": "Int", "config": {"name": "units_2", "default": null, "conditions": [], "min_value": 16, "max_value": 512, "step": 32, "sampling": "linear"}}, {"class_name": "Choice", "config": {"name": "activation_2", "default": "relu", "conditions": [], "values": ["relu", "leaky_relu", "swish", "gelu", "mish"], "ordered": false}}, {"class_name": "Float", "config": {"name": "dropout_2", "default": 0.1, "conditions": [], "min_value": 0.1, "max_value": 0.7, "step": 0.1, "sampling": "linear"}}, {"class_name": "Int", "config": {"name": "units_3", "default": null, "conditions": [], "min_value": 16, "max_value": 512, "step": 32, "sampling": "linear"}}, {"class_name": "Choice", "config": {"name": "activation_3", "default": "relu", "conditions": [], "values": ["relu", "leaky_relu", "swish", "gelu", "mish"], "ordered": false}}, {"class_name": "Float", "config": {"name": "dropout_3", "default": 0.1, "conditions": [], "min_value": 0.1, "max_value": 0.7, "step": 0.1, "sampling": "linear"}}, {"class_name": "Int", "config": {"name": "units_4", "default": null, "conditions": [], "min_value": 16, "max_value": 512, "step": 32, "sampling": "linear"}}, {"class_name": "Choice", "config": {"name": "activation_4", "default": "relu", "conditions": [], "values": ["relu", "leaky_relu", "swish", "gelu", "mish"], "ordered": false}}, {"class_name": "Float", "config": {"name": "dropout_4", "default": 0.1, "conditions": [], "min_value": 0.1, "max_value": 0.7, "step": 0.1, "sampling": "linear"}}, {"class_name": "Int", "config": {"name": "units_5", "default": null, "conditions": [], "min_value": 16, "max_value": 512, "step": 32, "sampling": "linear"}}, {"class_name": "Choice", "config": {"name": "activation_5", "default": "relu", "conditions": [], "values": ["relu", "leaky_relu", "swish", "gelu", "mish"], "ordered": false}}, {"class_name": "Float", "config": {"name": "dropout_5", "default": 0.1, "conditions": [], "min_value": 0.1, "max_value": 0.7, "step": 0.1, "sampling": "linear"}}, {"class_name": "Int", "config": {"name": "units_6", "default": null, "conditions": [], "min_value": 16, "max_value": 512, "step": 32, "sampling": "linear"}}, {"class_name": "Choice", "config": {"name": "activation_6", "default": "relu", "conditions": [], "values": ["relu", "leaky_relu", "swish", "gelu", "mish"], "ordered": false}}, {"class_name": "Float", "config": {"name": "dropout_6", "default": 0.1, "conditions": [], "min_value": 0.1, "max_value": 0.7, "step": 0.1, "sampling": "linear"}}, {"class_name": "Int", "config": {"name": "units_7", "default": null, "conditions": [], "min_value": 16, "max_value": 512, "step": 32, "sampling": "linear"}}, {"class_name": "Choice", "config": {"name": "activation_7", "default": "relu", "conditions": [], "values": ["relu", "leaky_relu", "swish", "gelu", "mish"], "ordered": false}}, {"class_name": "Float", "config": {"name": "dropout_7", "default": 0.1, "conditions": [], "min_value": 0.1, "max_value": 0.7, "step": 0.1, "sampling": "linear"}}, {"class_name": "Int", "config": {"name": "units_8", "default": null, "conditions": [], "min_value": 16, "max_value": 512, "step": 32, "sampling": "linear"}}, {"class_name": "Choice", "config": {"name": "activation_8", "default": "relu", "conditions": [], "values": ["relu", "leaky_relu", "swish", "gelu", "mish"], "ordered": false}}, {"class_name": "Float", "config": {"name": "dropout_8", "default": 0.1, "conditions": [], "min_value": 0.1, "max_value": 0.7, "step": 0.1, "sampling": "linear"}}, {"class_name": "Int", "config": {"name": "units_9", "default": null, "conditions": [], "min_value": 16, "max_value": 512, "step": 32, "sampling": "linear"}}, {"class_name": "Choice", "config": {"name": "activation_9", "default": "relu", "conditions": [], "values": ["relu", "leaky_relu", "swish", "gelu", "mish"], "ordered": false}}, {"class_name": "Float", "config": {"name": "dropout_9", "default": 0.1, "conditions": [], "min_value": 0.1, "max_value": 0.7, "step": 0.1, "sampling": "linear"}}, {"class_name": "Int", "config": {"name": "units_10", "default": null, "conditions": [], "min_value": 16, "max_value": 512, "step": 32, "sampling": "linear"}}, {"class_name": "Choice", "config": {"name": "activation_10", "default": "relu", "conditions": [], "values": ["relu", "leaky_relu", "swish", "gelu", "mish"], "ordered": false}}, {"class_name": "Float", "config": {"name": "dropout_10", "default": 0.1, "conditions": [], "min_value": 0.1, "max_value": 0.7, "step": 0.1, "sampling": "linear"}}, {"class_name": "Int", "config": {"name": "units_11", "default": null, "conditions": [], "min_value": 16, "max_value": 512, "step": 32, "sampling": "linear"}}, {"class_name": "Choice", "config": {"name": "activation_11", "default": "relu", "conditions": [], "values": ["relu", "leaky_relu", "swish", "gelu", "mish"], "ordered": false}}, {"class_name": "Float", "config": {"name": "dropout_11", "default": 0.1, "conditions": [], "min_value": 0.1, "max_value": 0.7, "step": 0.1, "sampling": "linear"}}, {"class_name": "Int", "config": {"name": "units_12", "default": null, "conditions": [], "min_value": 16, "max_value": 512, "step": 32, "sampling": "linear"}}, {"class_name": "Choice", "config": {"name": "activation_12", "default": "relu", "conditions": [], "values": ["relu", "leaky_relu", "swish", "gelu", "mish"], "ordered": false}}, {"class_name": "Float", "config": {"name": "dropout_12", "default": 0.1, "conditions": [], "min_value": 0.1, "max_value": 0.7, "step": 0.1, "sampling": "linear"}}, {"class_name": "Int", "config": {"name": "units_13", "default": null, "conditions": [], "min_value": 16, "max_value": 512, "step": 32, "sampling": "linear"}}, {"class_name": "Choice", "config": {"name": "activation_13", "default": "relu", "conditions": [], "values": ["relu", "leaky_relu", "swish", "gelu", "mish"], "ordered": false}}, {"class_name": "Float", "config": {"name": "dropout_13", "default": 0.1, "conditions": [], "min_value": 0.1, "max_value": 0.7, "step": 0.1, "sampling": "linear"}}, {"class_name": "Int", "config": {"name": "units_14", "default": null, "conditions": [], "min_value": 16, "max_value": 512, "step": 32, "sampling": "linear"}}, {"class_name": "Choice", "config": {"name": "activation_14", "default": "relu", "conditions": [], "values": ["relu", "leaky_relu", "swish", "gelu", "mish"], "ordered": false}}, {"class_name": "Float", "config": {"name": "dropout_14", "default": 0.1, "conditions": [], "min_value": 0.1, "max_value": 0.7, "step": 0.1, "sampling": "linear"}}, {"class_name": "Int", "config": {"name": "units_15", "default": null, "conditions": [], "min_value": 16, "max_value": 512, "step": 32, "sampling": "linear"}}, {"class_name": "Choice", "config": {"name": "activation_15", "default": "relu", "conditions": [], "values": ["relu", "leaky_relu", "swish", "gelu", "mish"], "ordered": false}}, {"class_name": "Float", "config": {"name": "dropout_15", "default": 0.1, "conditions": [], "min_value": 0.1, "max_value": 0.7, "step": 0.1, "sampling": "linear"}}, {"class_name": "Int", "config": {"name": "units_16", "default": null, "conditions": [], "min_value": 16, "max_value": 512, "step": 32, "sampling": "linear"}}, {"class_name": "Choice", "config": {"name": "activation_16", "default": "relu", "conditions": [], "values": ["relu", "leaky_relu", "swish", "gelu", "mish"], "ordered": false}}, {"class_name": "Float", "config": {"name": "dropout_16", "default": 0.1, "conditions": [], "min_value": 0.1, "max_value": 0.7, "step": 0.1, "sampling": "linear"}}, {"class_name": "Int", "config": {"name": "units_17", "default": null, "conditions": [], "min_value": 16, "max_value": 512, "step": 32, "sampling": "linear"}}, {"class_name": "Choice", "config": {"name": "activation_17", "default": "relu", "conditions": [], "values": ["relu", "leaky_relu", "swish", "gelu", "mish"], "ordered": false}}, {"class_name": "Float", "config": {"name": "dropout_17", "default": 0.1, "conditions": [], "min_value": 0.1, "max_value": 0.7, "step": 0.1, "sampling": "linear"}}, {"class_name": "Int", "config": {"name": "units_18", "default": null, "conditions": [], "min_value": 16, "max_value": 512, "step": 32, "sampling": "linear"}}, {"class_name": "Choice", "config": {"name": "activation_18", "default": "relu", "conditions": [], "values": ["relu", "leaky_relu", "swish", "gelu", "mish"], "ordered": false}}, {"class_name": "Float", "config": {"name": "dropout_18", "default": 0.1, "conditions": [], "min_value": 0.1, "max_value": 0.7, "step": 0.1, "sampling": "linear"}}, {"class_name": "Int", "config": {"name": "units_19", "default": null, "conditions": [], "min_value": 16, "max_value": 512, "step": 32, "sampling": "linear"}}, {"class_name": "Choice", "config": {"name": "activation_19", "default": "relu", "conditions": [], "values": ["relu", "leaky_relu", "swish", "gelu", "mish"], "ordered": false}}, {"class_name": "Float", "config": {"name": "dropout_19", "default": 0.1, "conditions": [], "min_value": 0.1, "max_value": 0.7, "step": 0.1, "sampling": "linear"}}], "values": {"num_layers": 17, "units_0": 432, "activation_0": "swish", "dropout_0": 0.2, "units_1": 464, "activation_1": "mish", "dropout_1": 0.4, "learning_rate": 0.005, "units_2": 336, "activation_2": "swish", "dropout_2": 0.5, "units_3": 80, "activation_3": "leaky_relu", "dropout_3": 0.5, "units_4": 112, "activation_4": "swish", "dropout_4": 0.4, "units_5": 464, "activation_5": "swish", "dropout_5": 0.2, "units_6": 464, "activation_6": "mish", "dropout_6": 0.2, "units_7": 240, "activation_7": "swish", "dropout_7": 0.5, "units_8": 112, "activation_8": "relu", "dropout_8": 0.4, "units_9": 304, "activation_9": "mish", "dropout_9": 0.30000000000000004, "units_10": 144, "activation_10": "gelu", "dropout_10": 0.5, "units_11": 400, "activation_11": "swish", "dropout_11": 0.30000000000000004, "units_12": 432, "activation_12": "mish", "dropout_12": 0.5, "units_13": 336, "activation_13": "leaky_relu", "dropout_13": 0.30000000000000004, "units_14": 496, "activation_14": "gelu", "dropout_14": 0.6, "units_15": 208, "activation_15": "gelu", "dropout_15": 0.2, "units_16": 336, "activation_16": "swish", "dropout_16": 0.30000000000000004, "units_17": 208, "activation_17": "relu", "dropout_17": 0.6, "units_18": 144, "activation_18": "relu", "dropout_18": 0.5, "units_19": 112, "activation_19": "relu", "dropout_19": 0.1}}, "metrics": {"metrics": {"loss": {"direction": "min", "observations": [{"value": [0.022501438856124878], "step": 64}]}, "mse": {"direction": "min", "observations": [{"value": [0.022501438856124878], "step": 64}]}, "val_loss": {"direction": "min", "observations": [{"value": [0.016841115429997444], "step": 64}]}, "val_mse": {"direction": "min", "observations": [{"value": [0.016841115429997444], "step": 64}]}, "learning_rate": {"direction": "min", "observations": [{"value": [0.0003435973485466093], "step": 64}]}}}, "score": 0.016841115429997444, "best_step": 64, "status": "COMPLETED", "message": null}