{"trial_id": "035", "hyperparameters": {"space": [{"class_name": "Int", "config": {"name": "num_layers", "default": null, "conditions": [], "min_value": 2, "max_value": 20, "step": 1, "sampling": "linear"}}, {"class_name": "Int", "config": {"name": "units_0", "default": null, "conditions": [], "min_value": 16, "max_value": 512, "step": 32, "sampling": "linear"}}, {"class_name": "Choice", "config": {"name": "activation_0", "default": "relu", "conditions": [], "values": ["relu", "leaky_relu", "swish", "gelu", "mish"], "ordered": false}}, {"class_name": "Float", "config": {"name": "dropout_0", "default": 0.1, "conditions": [], "min_value": 0.1, "max_value": 0.7, "step": 0.1, "sampling": "linear"}}, {"class_name": "Int", "config": {"name": "units_1", "default": null, "conditions": [], "min_value": 16, "max_value": 512, "step": 32, "sampling": "linear"}}, {"class_name": "Choice", "config": {"name": "activation_1", "default": "relu", "conditions": [], "values": ["relu", "leaky_relu", "swish", "gelu", "mish"], "ordered": false}}, {"class_name": "Float", "config": {"name": "dropout_1", "default": 0.1, "conditions": [], "min_value": 0.1, "max_value": 0.7, "step": 0.1, "sampling": "linear"}}, {"class_name": "Choice", "config": {"name": "learning_rate", "default": 0.005, "conditions": [], "values": [0.005, 0.001, 0.0005], "ordered": true}}, {"class_name": "Int", "config": {"name": "units_2", "default": null, "conditions": [], "min_value": 16, "max_value": 512, "step": 32, "sampling": "linear"}}, {"class_name": "Choice", "config": {"name": "activation_2", "default": "relu", "conditions": [], "values": ["relu", "leaky_relu", "swish", "gelu", "mish"], "ordered": false}}, {"class_name": "Float", "config": {"name": "dropout_2", "default": 0.1, "conditions": [], "min_value": 0.1, "max_value": 0.7, "step": 0.1, "sampling": "linear"}}, {"class_name": "Int", "config": {"name": "units_3", "default": null, "conditions": [], "min_value": 16, "max_value": 512, "step": 32, "sampling": "linear"}}, {"class_name": "Choice", "config": {"name": "activation_3", "default": "relu", "conditions": [], "values": ["relu", "leaky_relu", "swish", "gelu", "mish"], "ordered": false}}, {"class_name": "Float", "config": {"name": "dropout_3", "default": 0.1, "conditions": [], "min_value": 0.1, "max_value": 0.7, "step": 0.1, "sampling": "linear"}}, {"class_name": "Int", "config": {"name": "units_4", "default": null, "conditions": [], "min_value": 16, "max_value": 512, "step": 32, "sampling": "linear"}}, {"class_name": "Choice", "config": {"name": "activation_4", "default": "relu", "conditions": [], "values": ["relu", "leaky_relu", "swish", "gelu", "mish"], "ordered": false}}, {"class_name": "Float", "config": {"name": "dropout_4", "default": 0.1, "conditions": [], "min_value": 0.1, "max_value": 0.7, "step": 0.1, "sampling": "linear"}}, {"class_name": "Int", "config": {"name": "units_5", "default": null, "conditions": [], "min_value": 16, "max_value": 512, "step": 32, "sampling": "linear"}}, {"class_name": "Choice", "config": {"name": "activation_5", "default": "relu", "conditions": [], "values": ["relu", "leaky_relu", "swish", "gelu", "mish"], "ordered": false}}, {"class_name": "Float", "config": {"name": "dropout_5", "default": 0.1, "conditions": [], "min_value": 0.1, "max_value": 0.7, "step": 0.1, "sampling": "linear"}}, {"class_name": "Int", "config": {"name": "units_6", "default": null, "conditions": [], "min_value": 16, "max_value": 512, "step": 32, "sampling": "linear"}}, {"class_name": "Choice", "config": {"name": "activation_6", "default": "relu", "conditions": [], "values": ["relu", "leaky_relu", "swish", "gelu", "mish"], "ordered": false}}, {"class_name": "Float", "config": {"name": "dropout_6", "default": 0.1, "conditions": [], "min_value": 0.1, "max_value": 0.7, "step": 0.1, "sampling": "linear"}}, {"class_name": "Int", "config": {"name": "units_7", "default": null, "conditions": [], "min_value": 16, "max_value": 512, "step": 32, "sampling": "linear"}}, {"class_name": "Choice", "config": {"name": "activation_7", "default": "relu", "conditions": [], "values": ["relu", "leaky_relu", "swish", "gelu", "mish"], "ordered": false}}, {"class_name": "Float", "config": {"name": "dropout_7", "default": 0.1, "conditions": [], "min_value": 0.1, "max_value": 0.7, "step": 0.1, "sampling": "linear"}}, {"class_name": "Int", "config": {"name": "units_8", "default": null, "conditions": [], "min_value": 16, "max_value": 512, "step": 32, "sampling": "linear"}}, {"class_name": "Choice", "config": {"name": "activation_8", "default": "relu", "conditions": [], "values": ["relu", "leaky_relu", "swish", "gelu", "mish"], "ordered": false}}, {"class_name": "Float", "config": {"name": "dropout_8", "default": 0.1, "conditions": [], "min_value": 0.1, "max_value": 0.7, "step": 0.1, "sampling": "linear"}}, {"class_name": "Int", "config": {"name": "units_9", "default": null, "conditions": [], "min_value": 16, "max_value": 512, "step": 32, "sampling": "linear"}}, {"class_name": "Choice", "config": {"name": "activation_9", "default": "relu", "conditions": [], "values": ["relu", "leaky_relu", "swish", "gelu", "mish"], "ordered": false}}, {"class_name": "Float", "config": {"name": "dropout_9", "default": 0.1, "conditions": [], "min_value": 0.1, "max_value": 0.7, "step": 0.1, "sampling": "linear"}}, {"class_name": "Int", "config": {"name": "units_10", "default": null, "conditions": [], "min_value": 16, "max_value": 512, "step": 32, "sampling": "linear"}}, {"class_name": "Choice", "config": {"name": "activation_10", "default": "relu", "conditions": [], "values": ["relu", "leaky_relu", "swish", "gelu", "mish"], "ordered": false}}, {"class_name": "Float", "config": {"name": "dropout_10", "default": 0.1, "conditions": [], "min_value": 0.1, "max_value": 0.7, "step": 0.1, "sampling": "linear"}}, {"class_name": "Int", "config": {"name": "units_11", "default": null, "conditions": [], "min_value": 16, "max_value": 512, "step": 32, "sampling": "linear"}}, {"class_name": "Choice", "config": {"name": "activation_11", "default": "relu", "conditions": [], "values": ["relu", "leaky_relu", "swish", "gelu", "mish"], "ordered": false}}, {"class_name": "Float", "config": {"name": "dropout_11", "default": 0.1, "conditions": [], "min_value": 0.1, "max_value": 0.7, "step": 0.1, "sampling": "linear"}}, {"class_name": "Int", "config": {"name": "units_12", "default": null, "conditions": [], "min_value": 16, "max_value": 512, "step": 32, "sampling": "linear"}}, {"class_name": "Choice", "config": {"name": "activation_12", "default": "relu", "conditions": [], "values": ["relu", "leaky_relu", "swish", "gelu", "mish"], "ordered": false}}, {"class_name": "Float", "config": {"name": "dropout_12", "default": 0.1, "conditions": [], "min_value": 0.1, "max_value": 0.7, "step": 0.1, "sampling": "linear"}}, {"class_name": "Int", "config": {"name": "units_13", "default": null, "conditions": [], "min_value": 16, "max_value": 512, "step": 32, "sampling": "linear"}}, {"class_name": "Choice", "config": {"name": "activation_13", "default": "relu", "conditions": [], "values": ["relu", "leaky_relu", "swish", "gelu", "mish"], "ordered": false}}, {"class_name": "Float", "config": {"name": "dropout_13", "default": 0.1, "conditions": [], "min_value": 0.1, "max_value": 0.7, "step": 0.1, "sampling": "linear"}}, {"class_name": "Int", "config": {"name": "units_14", "default": null, "conditions": [], "min_value": 16, "max_value": 512, "step": 32, "sampling": "linear"}}, {"class_name": "Choice", "config": {"name": "activation_14", "default": "relu", "conditions": [], "values": ["relu", "leaky_relu", "swish", "gelu", "mish"], "ordered": false}}, {"class_name": "Float", "config": {"name": "dropout_14", "default": 0.1, "conditions": [], "min_value": 0.1, "max_value": 0.7, "step": 0.1, "sampling": "linear"}}, {"class_name": "Int", "config": {"name": "units_15", "default": null, "conditions": [], "min_value": 16, "max_value": 512, "step": 32, "sampling": "linear"}}, {"class_name": "Choice", "config": {"name": "activation_15", "default": "relu", "conditions": [], "values": ["relu", "leaky_relu", "swish", "gelu", "mish"], "ordered": false}}, {"class_name": "Float", "config": {"name": "dropout_15", "default": 0.1, "conditions": [], "min_value": 0.1, "max_value": 0.7, "step": 0.1, "sampling": "linear"}}, {"class_name": "Int", "config": {"name": "units_16", "default": null, "conditions": [], "min_value": 16, "max_value": 512, "step": 32, "sampling": "linear"}}, {"class_name": "Choice", "config": {"name": "activation_16", "default": "relu", "conditions": [], "values": ["relu", "leaky_relu", "swish", "gelu", "mish"], "ordered": false}}, {"class_name": "Float", "config": {"name": "dropout_16", "default": 0.1, "conditions": [], "min_value": 0.1, "max_value": 0.7, "step": 0.1, "sampling": "linear"}}, {"class_name": "Int", "config": {"name": "units_17", "default": null, "conditions": [], "min_value": 16, "max_value": 512, "step": 32, "sampling": "linear"}}, {"class_name": "Choice", "config": {"name": "activation_17", "default": "relu", "conditions": [], "values": ["relu", "leaky_relu", "swish", "gelu", "mish"], "ordered": false}}, {"class_name": "Float", "config": {"name": "dropout_17", "default": 0.1, "conditions": [], "min_value": 0.1, "max_value": 0.7, "step": 0.1, "sampling": "linear"}}, {"class_name": "Int", "config": {"name": "units_18", "default": null, "conditions": [], "min_value": 16, "max_value": 512, "step": 32, "sampling": "linear"}}, {"class_name": "Choice", "config": {"name": "activation_18", "default": "relu", "conditions": [], "values": ["relu", "leaky_relu", "swish", "gelu", "mish"], "ordered": false}}, {"class_name": "Float", "config": {"name": "dropout_18", "default": 0.1, "conditions": [], "min_value": 0.1, "max_value": 0.7, "step": 0.1, "sampling": "linear"}}], "values": {"num_layers": 17, "units_0": 272, "activation_0": "gelu", "dropout_0": 0.1, "units_1": 144, "activation_1": "relu", "dropout_1": 0.30000000000000004, "learning_rate": 0.001, "units_2": 272, "activation_2": "leaky_relu", "dropout_2": 0.6, "units_3": 240, "activation_3": "relu", "dropout_3": 0.4, "units_4": 304, "activation_4": "gelu", "dropout_4": 0.2, "units_5": 368, "activation_5": "relu", "dropout_5": 0.4, "units_6": 304, "activation_6": "leaky_relu", "dropout_6": 0.1, "units_7": 144, "activation_7": "relu", "dropout_7": 0.1, "units_8": 16, "activation_8": "mish", "dropout_8": 0.6, "units_9": 432, "activation_9": "swish", "dropout_9": 0.6, "units_10": 304, "activation_10": "gelu", "dropout_10": 0.4, "units_11": 112, "activation_11": "mish", "dropout_11": 0.5, "units_12": 80, "activation_12": "gelu", "dropout_12": 0.4, "units_13": 48, "activation_13": "leaky_relu", "dropout_13": 0.6, "units_14": 240, "activation_14": "swish", "dropout_14": 0.6, "units_15": 16, "activation_15": "gelu", "dropout_15": 0.4, "units_16": 48, "activation_16": "swish", "dropout_16": 0.1, "units_17": 400, "activation_17": "relu", "dropout_17": 0.4, "units_18": 400, "activation_18": "gelu", "dropout_18": 0.4}}, "metrics": {"metrics": {"loss": {"direction": "min", "observations": [{"value": [0.0063889422453939915], "step": 29}]}, "mse": {"direction": "min", "observations": [{"value": [0.0063889422453939915], "step": 29}]}, "val_loss": {"direction": "min", "observations": [{"value": [0.00465939287096262], "step": 29}]}, "val_mse": {"direction": "min", "observations": [{"value": [0.00465939287096262], "step": 29}]}, "learning_rate": {"direction": "min", "observations": [{"value": [0.0005120000569149852], "step": 29}]}}}, "score": 0.00465939287096262, "best_step": 29, "status": "COMPLETED", "message": null}